colander_tools/__init__.py
colander_tools/bytes.py
colander_tools/compat.py
colander_tools/mapping.py
colander_tools/netaddr.py
colander_tools/null.py
colander_tools/serializable.py
colander_tools/strict.py
colander_tools/subschema.py
colander_tools/test_bytes.py
colander_tools/test_mapping.py
colander_tools/test_null.py
colander_tools/test_strict.py
colander_tools/test_timezone.py
colander_tools/timezone.py
colander_tools/tests/__init__.py
colander_tools-0.13.0.dist-info/METADATA
colander_tools-0.13.0.dist-info/WHEEL
colander_tools-0.13.0.dist-info/top_level.txt
colander_tools-0.13.0.dist-info/RECORD
