Metadata-Version: 2.1
Name: colander_tools
Version: 0.13.0
Summary: Extensions to `colander`, particularly useful as part of REST API validation.
Home-page: https://github.com/platformsh/colander-tools
Author: Platform.sh
Author-email: sayhello@platform.sh
License: BSD
Classifier: Intended Audience :: Developers
Classifier: License :: OSI Approved :: BSD License
Classifier: Programming Language :: Python
Classifier: Programming Language :: Python :: 2.6
Classifier: Programming Language :: Python :: 2.7
Classifier: Programming Language :: Python :: 3
Requires-Dist: colander <3,>=2
Requires-Dist: pytz
Requires-Dist: netaddr
Requires-Dist: six
